setup.py
wealthpy/Asset.py
wealthpy/ETH.py
wealthpy/__init__.py
wealthpy.egg-info/PKG-INFO
wealthpy.egg-info/SOURCES.txt
wealthpy.egg-info/dependency_links.txt
wealthpy.egg-info/not-zip-safe
wealthpy.egg-info/top_level.txt