Metadata-Version: 1.0
Name: wealthpy
Version: 0.0.1
Summary: Sam.C's
Home-page: UNKNOWN
Author: UNKNOWN
Author-email: UNKNOWN
License: UNKNOWN
Platform: UNKNOWN
